MANIFEST.in
README.rst
setup.py
mdp_crawl_core/__init__.py
mdp_crawl_core.egg-info/PKG-INFO
mdp_crawl_core.egg-info/SOURCES.txt
mdp_crawl_core.egg-info/dependency_links.txt
mdp_crawl_core.egg-info/top_level.txt
mdp_crawl_core/client/__init__.py
mdp_crawl_core/client/async_mongo_client.py
mdp_crawl_core/client/async_rabbit_client.py
mdp_crawl_core/client/async_redis_client.py
mdp_crawl_core/exception/__init__.py
mdp_crawl_core/exception/exceptions.py
mdp_crawl_core/lib/__init__.py
mdp_crawl_core/lib/cfg.py
mdp_crawl_core/lib/func.py
mdp_crawl_core/lib/logger.py
mdp_crawl_core/lib/secret.py
mdp_crawl_core/lib/settings.py
mdp_crawl_core/lib/time.py
mdp_crawl_core/lib/util.py
mdp_crawl_core/utils/__init__.py
mdp_crawl_core/utils/common.py
mdp_crawl_core/utils/decator.py
mdp_crawl_core/utils/encryption.py
mdp_crawl_core/utils/sequence.py