Metadata-Version: 2.1
Name: mdp-crawl-core
Version: 0.0.4
Summary: mdp crawl core for zsodata
Home-page: http://www.zsodata.com
Author: zsodata
Author-email: team@zso.io
License: BSD License
Platform: all
Requires-Python: >=3.7
